setup.py
gopay_django_api/__init__.py
gopay_django_api/apps.py
gopay_django_api/models.py
gopay_django_api/signals.py
gopay_django_api/urls.py
gopay_django_api/views.py
gopay_django_api.egg-info/PKG-INFO
gopay_django_api.egg-info/SOURCES.txt
gopay_django_api.egg-info/dependency_links.txt
gopay_django_api.egg-info/requires.txt
gopay_django_api.egg-info/top_level.txt
gopay_django_api/management/__init__.py
gopay_django_api/management/commands/__init__.py
gopay_django_api/management/commands/gopay_create_payment.py
gopay_django_api/management/commands/refresh_payments.py
gopay_django_api/migrations/0001_initial.py
gopay_django_api/migrations/__init__.py