Metadata-Version: 1.0
Name: gopay-django-api
Version: 0.5
Summary: GoPay implemenation of API for Django
Home-page: https://github.com/papousek/gopay-django-api
Author: Jan Papousek
Author-email: jan.papousek@gmail.com
License: MIT
Platform: UNKNOWN
